setup.py
src/jld_osx/__init__.py
src/jld_osx.egg-info/PKG-INFO
src/jld_osx.egg-info/SOURCES.txt
src/jld_osx.egg-info/dependency_links.txt
src/jld_osx.egg-info/not-zip-safe
src/jld_osx.egg-info/requires.txt
src/jld_osx.egg-info/top_level.txt
src/jld_osx/itunes/__init__.py
src/jld_osx/itunes/helpers.py
src/jld_osx/scripts/__init__.py
src/jld_osx/scripts/itunes_update_playcount.py
src/scripts/itunes_update_playcount