Metadata-Version: 1.0
Name: jld-osx
Version: 0.1
Summary: Collection of python utility scripts for OSX
Home-page: http://www.systemical.com/doc/opensource/jld_osx
Author: Jean-Lou Dupont
Author-email: jl@jldupont.com
License: UNKNOWN
Platform: UNKNOWN
